threezh1mcptest/__init__.py
threezh1mcptest/main.py
threezh1mcptest-0.1.7.dist-info/METADATA
threezh1mcptest-0.1.7.dist-info/WHEEL
threezh1mcptest-0.1.7.dist-info/entry_points.txt
threezh1mcptest-0.1.7.dist-info/top_level.txt
threezh1mcptest-0.1.7.dist-info/RECORD
