Metadata-Version: 2.4
Name: threezh1mcptest
Version: 0.1.7
Summary: A simple example Python package
Home-page: https://github.com/yourusername/my_package
Author: Threezh1
Author-email: xiaothreezhi@example.com
Classifier: Programming Language :: Python :: 3
Classifier: License :: OSI Approved :: MIT License
Classifier: Operating System :: OS Independent
Requires-Python: >=3.6
Requires-Dist: mcp
Dynamic: author
Dynamic: author-email
Dynamic: classifier
Dynamic: description
Dynamic: description-content-type
Dynamic: home-page
Dynamic: requires-dist
Dynamic: requires-python
Dynamic: summary
